md_davis/__init__.py
md_davis/__main__.py
md_davis/amino_acids.py
md_davis/cli.py
md_davis/collate.py
md_davis/hbond.py
md_davis/process_gromacs_trajectory.py
md_davis/residue.py
md_davis/sequence.py
md_davis/xvg.py
md_davis/common/__init__.py
md_davis/common/my_matplotlib.py
md_davis/common/phylogenetic_tree.py
md_davis/common/polar.py
md_davis/common/rmsf_analysis.py
md_davis/common/schlitters_entropy.py
md_davis/common/secStr_counts.py
md_davis/common/stats.py
md_davis/common/utils.py
md_davis/electrostatics/__init__.py
md_davis/electrostatics/charmm.crg
md_davis/electrostatics/charmm.siz
md_davis/electrostatics/cube3.py
md_davis/electrostatics/electrodynamics.py
md_davis/electrostatics/electrostatics.py
md_davis/electrostatics/plot_electrostatics.py
md_davis/electrostatics/plot_potential.py
md_davis/electrostatics/potential_into_pdb.py
md_davis/electrostatics/vert2pdb.py
md_davis/gui/MD_DaVis.ico
md_davis/gui/__init__.py
md_davis/gui/__main__.py
md_davis/gui/collate_panel.py
md_davis/gui/electrodynamics_panel.py
md_davis/gui/electrostatics_panel.py
md_davis/gui/landscape_panel.py
md_davis/gui/residue_panel.py
md_davis/gui/sequence_panel.py
md_davis/landscape/__init__.py
md_davis/landscape/landscape.py
md_davis/landscape/landscape_animate.py
md_davis/landscape/landscape_hdf.py
md_davis/landscape/landscape_xvg.py
md_davis/plotting/__init__.py
md_davis/plotting/collect_data.py
md_davis/plotting/colors.py
md_davis/plotting/plot_aligned_residue_wise_data.py
md_davis/plotting/plot_dipoles.py
md_davis/plotting/plot_do_dssp_per_residue.py
md_davis/plotting/plot_dssp.py
md_davis/plotting/plot_hbond.py
md_davis/plotting/plot_hdf5_data.py
md_davis/plotting/plot_residue_dataframe.py
md_davis/plotting/plot_residue_wise_data_aligned.py
md_davis/plotting/plot_timeseries.py
md_davis/structure/__init__.py
md_davis/structure/center_orient.py
md_davis/structure/checkPDB.py
md_davis/structure/my_parser.py
md_davis/structure/rmsd.py
md_davis/structure/separate_chains.py
md_davis-0.4.1.dist-info/LICENSE
md_davis-0.4.1.dist-info/METADATA
md_davis-0.4.1.dist-info/WHEEL
md_davis-0.4.1.dist-info/entry_points.txt
md_davis-0.4.1.dist-info/top_level.txt
md_davis-0.4.1.dist-info/RECORD
