Metadata-Version: 2.1
Name: md-davis
Version: 0.4.1
Summary: A tool for comparative analysis of molecular dynamics simulations of proteins.
Home-page: https://github.com/djmaity/md-davis
Author: Dibyajyoti Maity
Author-email: djdibs@gmail.com
License: MIT license
Project-URL: Documentation, https://md-davis.readthedocs.io/
Project-URL: Changelog, https://md-davis.readthedocs.io/en/latest/changelog.html
Project-URL: Issue Tracker, https://github.com/djmaity/md-davis/issues
Keywords: analysis,data visualization,molecular dynamics,protein
Platform: UNKNOWN
Classifier: Development Status :: 4 - Beta
Classifier: Environment :: Console
Classifier: Intended Audience :: Science/Research
Classifier: License :: OSI Approved :: MIT License
Classifier: Natural Language :: English
Classifier: Operating System :: OS Independent
Classifier: Programming Language :: Python :: 3.7
Classifier: Programming Language :: Python :: 3.8
Classifier: Programming Language :: Python :: 3.9
Classifier: Programming Language :: Python :: 3.10
Classifier: Topic :: Scientific/Engineering :: Bio-Informatics
Classifier: Topic :: Scientific/Engineering :: Visualization
Requires-Python: >=3.6
License-File: LICENSE
Requires-Dist: biopandas
Requires-Dist: biopython
Requires-Dist: click
Requires-Dist: h5py
Requires-Dist: matplotlib
Requires-Dist: more-itertools
Requires-Dist: numpy
Requires-Dist: pandas
Requires-Dist: plotly
Requires-Dist: pmw
Requires-Dist: scikit-learn
Requires-Dist: scipy
Requires-Dist: toml
Requires-Dist: mdtraj
Requires-Dist: wxpython
